{
  "target": "target_h1",
  "device": "cuda",
  "trial_counts": {
    "total": 4,
    "ok": 4,
    "error": 0
  },
  "best_overall": [
    {
      "model_name": "GRU",
      "feature_group": "G4_price_plus_sentiment",
      "lag_window": 64,
      "hidden_size": 32,
      "lr": 0.0005,
      "epochs": 40,
      "patience": 8,
      "batch_size": 64,
      "target": "target_h1",
      "status": "ok",
      "note": "",
      "rmse": 0.010840007103979588,
      "mae": 0.007278326898813248,
      "directional_accuracy": 0.5,
      "sharpe": 1.006468033168798,
      "n_rows": 5286,
      "n_features": 36,
      "seq_len": 64,
      "n_test_total": 252,
      "avg_epochs_trained": 22.0,
      "artifact_path": "artifacts\\models\\deep_preprocessed_sentiment_seedhunt_h1\\target_h1\\target_h1_G4_price_plus_sentiment_GRU_lag64_h32_lr0.0005_e40_p8.pt"
    },
    {
      "model_name": "LSTM",
      "feature_group": "G5_sentiment_only",
      "lag_window": 64,
      "hidden_size": 32,
      "lr": 0.0005,
      "epochs": 40,
      "patience": 8,
      "batch_size": 64,
      "target": "target_h1",
      "status": "ok",
      "note": "",
      "rmse": 0.012973285280168056,
      "mae": 0.008471904322504997,
      "directional_accuracy": 0.5119047619047619,
      "sharpe": -0.4351330828023171,
      "n_rows": 5286,
      "n_features": 12,
      "seq_len": 64,
      "n_test_total": 252,
      "avg_epochs_trained": 18.666666666666668,
      "artifact_path": "artifacts\\models\\deep_preprocessed_sentiment_seedhunt_h1\\target_h1\\target_h1_G5_sentiment_only_LSTM_lag64_h32_lr0.0005_e40_p8.pt"
    },
    {
      "model_name": "LSTM",
      "feature_group": "G4_price_plus_sentiment",
      "lag_window": 64,
      "hidden_size": 32,
      "lr": 0.0005,
      "epochs": 40,
      "patience": 8,
      "batch_size": 64,
      "target": "target_h1",
      "status": "ok",
      "note": "",
      "rmse": 0.015363410115242004,
      "mae": 0.009287890046834946,
      "directional_accuracy": 0.503968253968254,
      "sharpe": 0.20921390153216535,
      "n_rows": 5286,
      "n_features": 36,
      "seq_len": 64,
      "n_test_total": 252,
      "avg_epochs_trained": 24.333333333333332,
      "artifact_path": "artifacts\\models\\deep_preprocessed_sentiment_seedhunt_h1\\target_h1\\target_h1_G4_price_plus_sentiment_LSTM_lag64_h32_lr0.0005_e40_p8.pt"
    },
    {
      "model_name": "GRU",
      "feature_group": "G5_sentiment_only",
      "lag_window": 64,
      "hidden_size": 32,
      "lr": 0.0005,
      "epochs": 40,
      "patience": 8,
      "batch_size": 64,
      "target": "target_h1",
      "status": "ok",
      "note": "",
      "rmse": 0.03972399979829788,
      "mae": 0.019812552258372307,
      "directional_accuracy": 0.5,
      "sharpe": -0.8937461801241762,
      "n_rows": 5286,
      "n_features": 12,
      "seq_len": 64,
      "n_test_total": 252,
      "avg_epochs_trained": 15.666666666666666,
      "artifact_path": "artifacts\\models\\deep_preprocessed_sentiment_seedhunt_h1\\target_h1\\target_h1_G5_sentiment_only_GRU_lag64_h32_lr0.0005_e40_p8.pt"
    }
  ],
  "best_primary": [],
  "best_baseline": [
    {
      "model_name": "GRU",
      "feature_group": "G4_price_plus_sentiment",
      "lag_window": 64,
      "hidden_size": 32,
      "lr": 0.0005,
      "epochs": 40,
      "patience": 8,
      "batch_size": 64,
      "target": "target_h1",
      "status": "ok",
      "note": "",
      "rmse": 0.010840007103979588,
      "mae": 0.007278326898813248,
      "directional_accuracy": 0.5,
      "sharpe": 1.006468033168798,
      "n_rows": 5286,
      "n_features": 36,
      "seq_len": 64,
      "n_test_total": 252,
      "avg_epochs_trained": 22.0,
      "artifact_path": "artifacts\\models\\deep_preprocessed_sentiment_seedhunt_h1\\target_h1\\target_h1_G4_price_plus_sentiment_GRU_lag64_h32_lr0.0005_e40_p8.pt"
    },
    {
      "model_name": "LSTM",
      "feature_group": "G5_sentiment_only",
      "lag_window": 64,
      "hidden_size": 32,
      "lr": 0.0005,
      "epochs": 40,
      "patience": 8,
      "batch_size": 64,
      "target": "target_h1",
      "status": "ok",
      "note": "",
      "rmse": 0.012973285280168056,
      "mae": 0.008471904322504997,
      "directional_accuracy": 0.5119047619047619,
      "sharpe": -0.4351330828023171,
      "n_rows": 5286,
      "n_features": 12,
      "seq_len": 64,
      "n_test_total": 252,
      "avg_epochs_trained": 18.666666666666668,
      "artifact_path": "artifacts\\models\\deep_preprocessed_sentiment_seedhunt_h1\\target_h1\\target_h1_G5_sentiment_only_LSTM_lag64_h32_lr0.0005_e40_p8.pt"
    },
    {
      "model_name": "LSTM",
      "feature_group": "G4_price_plus_sentiment",
      "lag_window": 64,
      "hidden_size": 32,
      "lr": 0.0005,
      "epochs": 40,
      "patience": 8,
      "batch_size": 64,
      "target": "target_h1",
      "status": "ok",
      "note": "",
      "rmse": 0.015363410115242004,
      "mae": 0.009287890046834946,
      "directional_accuracy": 0.503968253968254,
      "sharpe": 0.20921390153216535,
      "n_rows": 5286,
      "n_features": 36,
      "seq_len": 64,
      "n_test_total": 252,
      "avg_epochs_trained": 24.333333333333332,
      "artifact_path": "artifacts\\models\\deep_preprocessed_sentiment_seedhunt_h1\\target_h1\\target_h1_G4_price_plus_sentiment_LSTM_lag64_h32_lr0.0005_e40_p8.pt"
    },
    {
      "model_name": "GRU",
      "feature_group": "G5_sentiment_only",
      "lag_window": 64,
      "hidden_size": 32,
      "lr": 0.0005,
      "epochs": 40,
      "patience": 8,
      "batch_size": 64,
      "target": "target_h1",
      "status": "ok",
      "note": "",
      "rmse": 0.03972399979829788,
      "mae": 0.019812552258372307,
      "directional_accuracy": 0.5,
      "sharpe": -0.8937461801241762,
      "n_rows": 5286,
      "n_features": 12,
      "seq_len": 64,
      "n_test_total": 252,
      "avg_epochs_trained": 15.666666666666666,
      "artifact_path": "artifacts\\models\\deep_preprocessed_sentiment_seedhunt_h1\\target_h1\\target_h1_G5_sentiment_only_GRU_lag64_h32_lr0.0005_e40_p8.pt"
    }
  ]
}